CHANGES.txt
LICENSE.txt
MANIFEST.in
README.rst
setup.cfg
setup.py
corneti/__init__.py
corneti.recipes.codeintel.egg-info/PKG-INFO
corneti.recipes.codeintel.egg-info/SOURCES.txt
corneti.recipes.codeintel.egg-info/dependency_links.txt
corneti.recipes.codeintel.egg-info/entry_points.txt
corneti.recipes.codeintel.egg-info/namespace_packages.txt
corneti.recipes.codeintel.egg-info/not-zip-safe
corneti.recipes.codeintel.egg-info/requires.txt
corneti.recipes.codeintel.egg-info/top_level.txt
corneti/recipes/__init__.py
corneti/recipes/codeintel/__init__.py
corneti/recipes/codeintel/tests/__init__.py
corneti/recipes/codeintel/tests/test_docs.py