Metadata-Version: 1.1
Name: corneti.recipes.codeintel
Version: 0.3
Summary: A Sublime Text 2 / SublimeCodeIntel auto-completion data generator for buildout
Home-page: https://github.com/fabiocorneti/corneti.recipes.codeintel
Author: Fabio Corneti
Author-email: info@corneti.com
License: MIT
Keywords: sublimetext sublimecodeintel editor buildout recipe
Platform: UNKNOWN
Classifier: Development Status :: 4 - Beta
Classifier: Environment :: Console
Classifier: Framework :: Buildout
Classifier: Framework :: Buildout :: Recipe
Classifier: Intended Audience :: Developers
Classifier: License :: OSI Approved :: MIT License
Classifier: Operating System :: OS Independent
Classifier: Programming Language :: Python
Classifier: Topic :: Text Editors
